abieos/__init__.py
abieos/_private.c
abieos/_private.cpython-37m-darwin.so
abieos/private.py
abieos/serializer.py
abieos_python-1.0.0.dist-info/LICENSE
abieos_python-1.0.0.dist-info/METADATA
abieos_python-1.0.0.dist-info/WHEEL
abieos_python-1.0.0.dist-info/top_level.txt
abieos_python-1.0.0.dist-info/RECORD
