Metadata-Version: 2.1
Name: abieos-python
Version: 1.0.0
Summary: Python bindings for abieos library.
Home-page: https://github.com/ulamlabs/abieos-python
Author: Maciej Janiszewski
Author-email: maciej@ulam.io
License: MIT License
Platform: UNKNOWN
